vimseo/.coveragerc
vimseo/VIMS_GISEH_CONFIG.config_bkp
vimseo/__init__.py
vimseo/api.py
vimseo/config/__init__.py
vimseo/config/config_components.py
vimseo/config/global_configuration.py
vimseo/core/__init__.py
vimseo/core/base_component.py
vimseo/core/base_discipline_model.py
vimseo/core/base_integrated_model.py
vimseo/core/factory.py
vimseo/core/gemseo_discipline_wrapper.py
vimseo/core/inputs_handler.py
vimseo/core/load.py
vimseo/core/load_case.py
vimseo/core/load_case_factory.py
vimseo/core/model_description.py
vimseo/core/model_factory.py
vimseo/core/model_metadata.py
vimseo/core/model_result.py
vimseo/core/pre_run_post_model.py
vimseo/core/components/__init__.py
vimseo/core/components/component_factory.py
vimseo/core/components/discipline_wrapper_component.py
vimseo/core/components/external_software_component.py
vimseo/core/components/library_file.py
vimseo/core/components/post/__init__.py
vimseo/core/components/post/post_processor.py
vimseo/core/components/pre/__init__.py
vimseo/core/components/pre/pre_processor.py
vimseo/core/components/run/__init__.py
vimseo/core/components/run/run_processor.py
vimseo/core/components/subroutines/__init__.py
vimseo/core/components/subroutines/subroutine_wrapper.py
vimseo/core/components/subroutines/subroutine_wrapper_factory.py
vimseo/direct_measures/__init__.py
vimseo/direct_measures/curve_measure.py
vimseo/direct_measures/direct_measure.py
vimseo/direct_measures/direct_measure_factory.py
vimseo/io/__init__.py
vimseo/io/base_tool_io.py
vimseo/io/io_factory.py
vimseo/io/space_io.py
vimseo/io/test_data/__init__.py
vimseo/io/test_data/dataset/__init__.py
vimseo/io/test_data/dataset/dataframe_vectors.csv
vimseo/io/test_data/dataset/dataframe_vectors_component_indexing.csv
vimseo/io/test_data/dataset/experimental_scalars.csv
vimseo/io/test_data/space_tool/__init__.py
vimseo/io/test_data/space_tool/space_tool_result.json
vimseo/job_executor/__init__.py
vimseo/job_executor/base_executor.py
vimseo-0.1.5.dist-info/licenses/LICENSE.txt
vimseo-0.1.5.dist-info/METADATA
vimseo-0.1.5.dist-info/WHEEL
vimseo-0.1.5.dist-info/entry_points.txt
vimseo-0.1.5.dist-info/top_level.txt
vimseo-0.1.5.dist-info/RECORD
