Metadata-Version: 2.4
Name: vimseo
Version: 0.1.5
Summary: A framework for the demonstration of simulation credibility, enabling Qualification/Certification by Analysis supported by tests.
Author-email: VIMSEO developers <sebastien.bocquet@irt-saintexupery.com>
License-Expression: LGPL-3.0
Project-URL: Homepage, https://gemseo.org
Project-URL: Source, https://github.com/SebastienBocquet/vimseo
Project-URL: Issues, https://github.com/SebastienBocquet/vimseo/issues
Classifier: Intended Audience :: Science/Research
Classifier: Topic :: Scientific/Engineering
Classifier: Operating System :: POSIX :: Linux
Classifier: Operating System :: MacOS
Classifier: Operating System :: Microsoft :: Windows
Classifier: Programming Language :: Python :: 3 :: Only
Classifier: Programming Language :: Python :: 3.10
Classifier: Programming Language :: Python :: 3.11
Classifier: Programming Language :: Python :: 3.12
Requires-Python: <3.13,>=3.10
License-File: LICENSE.txt
Requires-Dist: plotly<=5.24.0,>=5.15.0
Requires-Dist: nbformat<=5.10.4,>=4.2.0
Requires-Dist: future<=1.0.0,>=1.0.0
Requires-Dist: gemseo-vimseo[all]<7,>=6
Requires-Dist: PyYAML<=6.0.3,>=6.0.2
Requires-Dist: pytest-csv<=3.0.0,>=3.0.0
Requires-Dist: statsmodels<=0.14.5,>=0.14.4
Requires-Dist: eval-type-backport<=0.2.2,>=0.2.2
Requires-Dist: gemseo_calibration-vimseo<4,>=3.0.2
Requires-Dist: seaborn<=0.13.2,>=0.13.2
Requires-Dist: meshio<=5.3.5,>=5.3.5
Requires-Dist: mlflow<=3.5.1,>=3.5.1
Requires-Dist: emcee<=3.1.6,>=3.1.6
Requires-Dist: openturns<=1.24,>=1.24
Requires-Dist: pydantic-settings
Dynamic: license-file
